convertRobotVoiceToVoiceX.py
example.py
voicex/TTS.py
voicex/Voices.py
voicex/__init__.py
voicex/res/logo.png
voicex/voices/andrea.voicex
voicex/voices/drw_female_1.voicex
voicex/voices/drw_female_2.voicex
voicex/voices/drw_female_3.voicex
voicex/voices/elisabeth_old.voicex
voicex/voices/gabby.voicex
voicex/voices/granny.voicex
voicex/voices/kimberly.voicex
voicex/voices/lenny.voicex
voicex/voices/lisa_old.voicex
voicex/voices/male_depressed.voicex
voicex/voices/male_shy_1.voicex
voicex/voices/male_shy_2.voicex
voicex/voices/silvan.voicex
voicex-1.1.7.dist-info/LICENSE
voicex-1.1.7.dist-info/METADATA
voicex-1.1.7.dist-info/WHEEL
voicex-1.1.7.dist-info/top_level.txt
voicex-1.1.7.dist-info/RECORD
