Metadata-Version: 2.1
Name: voicex
Version: 1.1.7
Summary: TTS system with fully customizable voices.
Author-email: Silvan Mertes <silvan.mertes@informatik.uni-augsburg.de>
Project-URL: Homepage, https://github.com/hcmlab/voicex
Classifier: License :: OSI Approved :: MIT License
Classifier: Programming Language :: Python
Classifier: Programming Language :: Python :: 3
Requires-Python: >=3.5
License-File: LICENSE
Requires-Dist: scipy
Requires-Dist: sounddevice
Requires-Dist: numpy
Requires-Dist: requests
